misspell/__init__.py
misspell-0.6.data/scripts/__init__.py
misspell-0.6.dist-info/LICENSE
misspell-0.6.dist-info/METADATA
misspell-0.6.dist-info/WHEEL
misspell-0.6.dist-info/top_level.txt
misspell-0.6.dist-info/RECORD
