Metadata-Version: 2.1
Name: misspell
Version: 0.6
Summary: Some functions that introduce random typographical errors in provided text.
Home-page: https://github.com/MrMebelMan/misspell
Author: Vladyslav Burzakovskyy
Author-email: mutex-lock@protonmail.com
License: UNKNOWN
Platform: UNKNOWN
Classifier: Programming Language :: Python :: 3
Classifier: Operating System :: OS Independent
